.gitignore
LICENSE
Makefile
README.rst
requirements.txt
setup.cfg
setup.py
data/config-example.ini
debug/client.py
debug/server.py
socklet/.gitignore
socklet/__init__.py
socklet/__main__.py
socklet/arguments.py
socklet/config.py
socklet/decorators.py
socklet/event.py
socklet/exception.py
socklet/logging.py
socklet/namespace.py
socklet/server.py
socklet/socklet.py
socklet/util.py
socklet/version.py
socklet.egg-info/PKG-INFO
socklet.egg-info/SOURCES.txt
socklet.egg-info/dependency_links.txt
socklet.egg-info/entry_points.txt
socklet.egg-info/requires.txt
socklet.egg-info/top_level.txt