Metadata-Version: 1.2
Name: socklet
Version: 1.0.1
Summary: A tool for bridging Socket.IO 0.9 to WebSocket.
Home-page: https://pypi.python.org/pypi/socklet
Author: eikendev, leopoldsedev
Author-email: raphael@eiken.dev, christian@leopoldse.dev
License: MIT
Keywords: socket-io,websocket,bridge
Platform: UNKNOWN
Classifier: Development Status :: 4 - Beta
Classifier: Intended Audience :: Developers
Classifier: License :: OSI Approved :: MIT License
Classifier: Programming Language :: Python :: 3
Classifier: Topic :: Utilities
Classifier: Environment :: Console
Classifier: Operating System :: POSIX
Requires-Python: >=3
